source_freshdesk/__init__.py
source_freshdesk/components.py
source_freshdesk/manifest.yaml
source_freshdesk/run.py
source_freshdesk/schemas/agents.json
source_freshdesk/schemas/business_hours.json
source_freshdesk/schemas/canned_response_folders.json
source_freshdesk/schemas/canned_responses.json
source_freshdesk/schemas/companies.json
source_freshdesk/schemas/contacts.json
source_freshdesk/schemas/conversations.json
source_freshdesk/schemas/discussion_categories.json
source_freshdesk/schemas/discussion_comments.json
source_freshdesk/schemas/discussion_forums.json
source_freshdesk/schemas/discussion_topics.json
source_freshdesk/schemas/email_configs.json
source_freshdesk/schemas/email_mailboxes.json
source_freshdesk/schemas/groups.json
source_freshdesk/schemas/products.json
source_freshdesk/schemas/roles.json
source_freshdesk/schemas/satisfaction_ratings.json
source_freshdesk/schemas/scenario_automations.json
source_freshdesk/schemas/settings.json
source_freshdesk/schemas/skills.json
source_freshdesk/schemas/sla_policies.json
source_freshdesk/schemas/solution_articles.json
source_freshdesk/schemas/solution_categories.json
source_freshdesk/schemas/solution_folders.json
source_freshdesk/schemas/surveys.json
source_freshdesk/schemas/ticket_fields.json
source_freshdesk/schemas/tickets.json
source_freshdesk/schemas/time_entries.json
source_freshdesk/source.py
source_freshdesk/utils.py
airbyte_source_freshdesk-3.1.3.dist-info/METADATA
airbyte_source_freshdesk-3.1.3.dist-info/WHEEL
airbyte_source_freshdesk-3.1.3.dist-info/entry_points.txt
airbyte_source_freshdesk-3.1.3.dist-info/RECORD
