Metadata-Version: 2.3
Name: airbyte-source-freshdesk
Version: 3.1.3
Summary: Source implementation for Freshdesk.
License: MIT
Author: Airbyte
Author-email: contact@airbyte.io
Requires-Python: >=3.9,<3.12
Classifier: License :: OSI Approved :: MIT License
Classifier: Programming Language :: Python :: 3
Classifier: Programming Language :: Python :: 3.9
Classifier: Programming Language :: Python :: 3.10
Classifier: Programming Language :: Python :: 3.11
Requires-Dist: airbyte-cdk (>=0,<1)
Requires-Dist: backoff (==1.10.0)
Project-URL: Documentation, https://docs.airbyte.com/integrations/sources/freshdesk
Project-URL: Homepage, https://airbyte.com
Project-URL: Repository, https://github.com/airbytehq/airbyte
